src/__init__.py
src/coaching/__init__.py
src/coaching/personas.py
src/coaching/prompts.py
src/coaching/sampling.py
src/models/__init__.py
src/models/combat_log.py
src/models/filters.py
src/models/game_context.py
src/models/hero_counters.py
src/models/map_data.py
src/models/match_info.py
src/models/pro_scene.py
src/models/tool_responses.py
src/models/types.py
src/prompts/__init__.py
src/prompts/mcp_prompts.py
src/resources/heroes_resources.py
src/resources/map_resources.py
src/resources/pro_scene_resources.py
src/resources/versioned_map_resources.py
src/services/__init__.py
src/services/analyzers/__init__.py
src/services/analyzers/fight_analyzer.py
src/services/analyzers/fight_detector.py
src/services/cache/__init__.py
src/services/cache/replay_cache.py
src/services/combat/__init__.py
src/services/combat/combat_service.py
src/services/combat/fight_service.py
src/services/farming/__init__.py
src/services/farming/farming_service.py
src/services/jungle/__init__.py
src/services/jungle/jungle_service.py
src/services/lane/__init__.py
src/services/lane/lane_service.py
src/services/models/__init__.py
src/services/models/combat_data.py
src/services/models/farming_data.py
src/services/models/jungle_data.py
src/services/models/lane_data.py
src/services/models/replay_data.py
src/services/models/rotation_data.py
src/services/models/seek_data.py
src/services/replay/__init__.py
src/services/replay/replay_service.py
src/services/rotation/__init__.py
src/services/rotation/rotation_service.py
src/services/seek/__init__.py
src/services/seek/seek_service.py
src/tools/__init__.py
src/tools/analysis_tools.py
src/tools/combat_tools.py
src/tools/fight_tools.py
src/tools/match_tools.py
src/tools/pro_scene_tools.py
src/tools/replay_tools.py
src/utils/__init__.py
src/utils/constants.py
src/utils/constants_fetcher.py
src/utils/hero_fuzzy_search.py
src/utils/hero_resolver.py
src/utils/league_fuzzy_search.py
src/utils/match_fetcher.py
src/utils/match_info_parser.py
mcp_replay_dota2-1.2.0.dist-info/METADATA
mcp_replay_dota2-1.2.0.dist-info/WHEEL
mcp_replay_dota2-1.2.0.dist-info/entry_points.txt
mcp_replay_dota2-1.2.0.dist-info/licenses/LICENSE
mcp_replay_dota2-1.2.0.dist-info/RECORD
