Metadata-Version: 2.4
Name: mcp-replay-dota2
Version: 1.2.0
Summary: Model Context Protocol server for Dota 2 match analysis using replay files
Project-URL: Homepage, https://github.com/DeepBlueCoding/mcp-replay-dota2
Project-URL: Documentation, https://deepbluecoding.github.io/mcp-replay-dota2/
Project-URL: Repository, https://github.com/DeepBlueCoding/mcp-replay-dota2
Project-URL: Bug Tracker, https://github.com/DeepBlueCoding/mcp-replay-dota2/issues
License-Expression: MIT
License-File: LICENSE
Keywords: analysis,dota2,esports,mcp,model-context-protocol,replay
Classifier: Development Status :: 3 - Alpha
Classifier: Intended Audience :: Developers
Classifier: Programming Language :: Python :: 3.12
Classifier: Topic :: Games/Entertainment
Requires-Python: <3.13,>=3.12
Requires-Dist: aiohttp>=3.13.2
Requires-Dist: anthropic>=0.75.0
Requires-Dist: diskcache>=5.6.3
Requires-Dist: fastmcp>=2.12.3
Requires-Dist: python-manta==1.4.7.3
Requires-Dist: python-opendota-sdk>=7.40.3
Requires-Dist: requests>=2.32.5
Provides-Extra: dev
Requires-Dist: ipykernel>=6.30.1; extra == 'dev'
Requires-Dist: jupyter>=1.1.1; extra == 'dev'
Requires-Dist: pip>=25.0; extra == 'dev'
Requires-Dist: pytest-asyncio>=1.3.0; extra == 'dev'
Requires-Dist: pytest>=8.4.2; extra == 'dev'
